sentient/__init__.py
sentient/main.py
sentient/modules/Email_Lookup.py
sentient/modules/Email_Tracker.py
sentient/modules/Phone_Lookup.py
sentient/modules/__init__.py
sentient/modules/breach_checker.py
sentient/modules/cve_search.py
sentient/modules/dir_bruteforce.py
sentient/modules/dns_tools.py
sentient/modules/email_spoof_test.py
sentient/modules/file_analysis.py
sentient/modules/geoip_lookup.py
sentient/modules/hash_tools.py
sentient/modules/image_metadata.py
sentient/modules/jwt_analyzer.py
sentient/modules/log_analyzer.py
sentient/modules/packet_analyzer.py
sentient/modules/password_strength.py
sentient/modules/pdf_analyzer.py
sentient/modules/port_scanner.py
sentient/modules/real_traffic.py
sentient/modules/reverse_ip.py
sentient/modules/ssl_checker.py
sentient/modules/subdomain_enum.py
sentient/modules/subdomain_takeover.py
sentient/modules/traffic_sender.py
sentient/modules/url_expander.py
sentient/modules/username_checker.py
sentient/modules/virustotal_scan.py
sentient/modules/website_scanner.py
sentient/modules/whois_lookup.py
sentient_ai-1.0.3.dist-info/METADATA
sentient_ai-1.0.3.dist-info/WHEEL
sentient_ai-1.0.3.dist-info/entry_points.txt
sentient_ai-1.0.3.dist-info/top_level.txt
sentient_ai-1.0.3.dist-info/RECORD
