Metadata-Version: 2.4
Name: sentient-ai
Version: 1.0.3
Summary: AI-powered cybersecurity and automation toolkit
Home-page: https://github.com/x0as/Sentient
Author: x0as
Author-email: muhammadhuzaifakhalidaziz@gmail.com
Project-URL: Bug Reports, https://github.com/x0as/Sentient/issues
Project-URL: Source, https://github.com/x0as/Sentient
Keywords: cybersecurity,automation,ai,hacking,penetration-testing,osint
Classifier: Development Status :: 4 - Beta
Classifier: Intended Audience :: Information Technology
Classifier: Topic :: Security
Classifier: License :: Other/Proprietary License
Classifier: Programming Language :: Python :: 3
Classifier: Programming Language :: Python :: 3.7
Classifier: Programming Language :: Python :: 3.8
Classifier: Programming Language :: Python :: 3.9
Classifier: Programming Language :: Python :: 3.10
Classifier: Programming Language :: Python :: 3.11
Classifier: Operating System :: OS Independent
Requires-Python: >=3.7
Requires-Dist: requests>=2.25.1
Requires-Dist: google-generativeai>=0.3.0
Requires-Dist: pymongo>=4.0.0
Requires-Dist: beautifulsoup4>=4.9.3
Requires-Dist: phonenumbers>=8.12.0
Requires-Dist: Pillow>=8.0.0
Requires-Dist: selenium>=3.141.0
Requires-Dist: dnspython>=2.1.0
Requires-Dist: tabulate>=0.8.9
Requires-Dist: fuzzywuzzy>=0.18.0
Requires-Dist: python-Levenshtein>=0.12.2
Requires-Dist: dnspython>=2.1.0
Requires-Dist: python-whois>=0.7.3
Requires-Dist: cryptography>=3.4.8
Requires-Dist: scapy>=2.4.5
Requires-Dist: colorama>=0.4.4
Requires-Dist: google-search-results>=2.4.0
Requires-Dist: fastapi>=0.68.0
Requires-Dist: uvicorn>=0.15.0
Requires-Dist: whois>=0.9.13
Provides-Extra: dev
Requires-Dist: pytest>=6.0; extra == "dev"
Requires-Dist: black>=21.0; extra == "dev"
Requires-Dist: flake8>=3.8; extra == "dev"
Requires-Dist: mypy>=0.812; extra == "dev"
Dynamic: author
Dynamic: author-email
Dynamic: classifier
Dynamic: description
Dynamic: description-content-type
Dynamic: home-page
Dynamic: keywords
Dynamic: project-url
Dynamic: provides-extra
Dynamic: requires-dist
Dynamic: requires-python
Dynamic: summary
